budgetnlp/__init__.py
budgetnlp/calculate_drift_score.py
budgetnlp/extract_contexts.py
budgetnlp/loughran_mcdonald.py
budgetnlp/utils/__init__.py
budgetnlp/utils/download_data.py
budgetnlp/utils/text_normalization.py
budgetnlp-0.0.3.dist-info/licenses/LICENSE
budgetnlp-0.0.3.dist-info/METADATA
budgetnlp-0.0.3.dist-info/WHEEL
budgetnlp-0.0.3.dist-info/top_level.txt
budgetnlp-0.0.3.dist-info/RECORD
