Metadata-Version: 2.4
Name: budgetnlp
Version: 0.0.3
Summary: NLP on a budget
License: MIT
License-File: LICENSE
Requires-Dist: flashtext
Dynamic: description
Dynamic: description-content-type
Dynamic: license
Dynamic: license-file
Dynamic: requires-dist
Dynamic: summary
